README.md
setup.cfg
setup.py
src/letmein/__init__.py
src/letmein/backends.py
src/letmein/instrumentation.py
src/letmein/logic.py
src/letmein/middleware.py
src/letmein/settings.py
src/letmein/signals.py
src/letmein/utils.py
src/letmein.egg-info/PKG-INFO
src/letmein.egg-info/SOURCES.txt
src/letmein.egg-info/dependency_links.txt
src/letmein.egg-info/requires.txt
src/letmein.egg-info/top_level.txt
src/letmein/model/__init__.py
src/letmein/model/user/__init__.py
src/letmein/model/user/columns.py
src/letmein/model/user/facade.py
src/letmein/model/user/mixins.py