Metadata-Version: 1.1
Name: letmein
Version: 0.0.1a2
Summary: Drop in replacement for django.contrib.auth in a modelchemy context
Home-page: https://github.com/rjusher/letmein
Author: Raymond Joseph Usher Roche
Author-email: rjusher+pypi@gmail.com
License: BSD
Download-URL: https://github.com/rjusher/letmein/archive/v0.0.1-alpha1.tar.gz
Keywords: django,sqlalchemy
Platform: UNKNOWN
Classifier: Topic :: Database :: Front-Ends
Classifier: Programming Language :: Python
Classifier: Intended Audience :: Developers
Classifier: Environment :: Web Environment
Classifier: Framework :: Django
Classifier: Programming Language :: Python :: 3.6
Classifier: Topic :: Internet :: WWW/HTTP
Classifier: Topic :: Internet :: WWW/HTTP :: Dynamic Content
Classifier: Topic :: Internet :: WWW/HTTP :: WSGI
Classifier: Topic :: Software Development :: Libraries :: Application Frameworks
Classifier: Topic :: Software Development :: Libraries :: Python Modules
Classifier: License :: OSI Approved :: BSD License
